rapidocr_openvinogpu/__init__.py
rapidocr_openvinogpu/config.yaml
rapidocr_openvinogpu/rapid_ocr_api.py
rapidocr_openvinogpu/utils.py
rapidocr_openvinogpu/ch_ppocr_v2_cls/__init__.py
rapidocr_openvinogpu/ch_ppocr_v2_cls/config.yaml
rapidocr_openvinogpu/ch_ppocr_v2_cls/text_cls.py
rapidocr_openvinogpu/ch_ppocr_v2_cls/utils.py
rapidocr_openvinogpu/ch_ppocr_v3_det/__init__.py
rapidocr_openvinogpu/ch_ppocr_v3_det/config.yaml
rapidocr_openvinogpu/ch_ppocr_v3_det/text_detect.py
rapidocr_openvinogpu/ch_ppocr_v3_det/utils.py
rapidocr_openvinogpu/ch_ppocr_v3_rec/__init__.py
rapidocr_openvinogpu/ch_ppocr_v3_rec/config.yaml
rapidocr_openvinogpu/ch_ppocr_v3_rec/ppocr_keys_v1.txt
rapidocr_openvinogpu/ch_ppocr_v3_rec/text_recognize.py
rapidocr_openvinogpu/ch_ppocr_v3_rec/utils.py
rapidocr_openvinogpu/models/ch_PP-OCRv2_det_infer.onnx
rapidocr_openvinogpu/models/ch_PP-OCRv2_rec_infer.onnx
rapidocr_openvinogpu/models/ch_PP-OCRv3_det_infer.onnx
rapidocr_openvinogpu/models/ch_PP-OCRv3_rec_infer.onnx
rapidocr_openvinogpu/models/ch_PP-OCRv3_rec_train_student.onnx
rapidocr_openvinogpu/models/ch_PP-OCRv3_rec_train_teacher.onnx
rapidocr_openvinogpu/models/ch_ppocr_mobile_v2.0_cls_infer.onnx
rapidocr_openvinogpu/models/ch_ppocr_mobile_v2.0_cls_train.onnx
rapidocr_openvinogpu/models/en_PP-OCRv3_rec_infer.onnx
rapidocr_openvinogpu-0.0.9.dist-info/LICENSE.txt
rapidocr_openvinogpu-0.0.9.dist-info/METADATA
rapidocr_openvinogpu-0.0.9.dist-info/WHEEL
rapidocr_openvinogpu-0.0.9.dist-info/top_level.txt
rapidocr_openvinogpu-0.0.9.dist-info/RECORD
