Metadata-Version: 2.1
Name: rapidocr-openvinogpu
Version: 0.0.9
Summary: RapidOCR OpenVINO GPU version (GPU version only)
Author-email: Jagadish <jagadishkmahendran@gmail.com>
License: Apache License
Project-URL: repository, https://github.com/jaggiK/rapidocr_openvinogpu
Project-URL: issues, https://github.com/jaggiK/rapidocr_openvinogpu/issues
Keywords: ocr,text_detection,text_recognition,db,onnxruntime,paddleocr,openvino,rapidocr
Platform: Any
Classifier: Programming Language :: Python :: 3.7
Classifier: Programming Language :: Python :: 3.8
Classifier: Programming Language :: Python :: 3.9
Classifier: Programming Language :: Python :: 3.10
Classifier: Programming Language :: Python :: 3.11
Requires-Python: >=3.6,<=3.11
License-File: LICENSE.txt
Requires-Dist: pyclipper (>=1.2.1)
Requires-Dist: openvino (>=2022.2.0)
Requires-Dist: opencv-python (>=4.5.1.48)
Requires-Dist: numpy (>=1.19.3)
Requires-Dist: six (>=1.15.0)
Requires-Dist: Shapely (>=1.7.1)
Requires-Dist: PyYAML
Requires-Dist: Pillow
